LICENSE.txt
MANIFEST.in
README.txt
VERSION.txt
django_recaptcha_field.py
setup.cfg
setup.py
django_recaptcha_field.egg-info/PKG-INFO
django_recaptcha_field.egg-info/SOURCES.txt
django_recaptcha_field.egg-info/dependency_links.txt
django_recaptcha_field.egg-info/not-zip-safe
django_recaptcha_field.egg-info/requires.txt
django_recaptcha_field.egg-info/top_level.txt